oilvisco/__init__.py
oilvisco/__main__.py
oilvisco/calc.py
oilvisco/datatypes.py
oilvisco/ui.py
oilvisco-23.1.31.1.dist-info/METADATA
oilvisco-23.1.31.1.dist-info/WHEEL
oilvisco-23.1.31.1.dist-info/entry_points.txt
oilvisco-23.1.31.1.dist-info/RECORD
