Metadata-Version: 2.1
Name: oilvisco
Version: 23.1.31.1
Summary: Calculates the blended viscosity of different motor oils, when mixed together.
Project-URL: Homepage, https://github.com/Exsplendor/oilvisco
Project-URL: Bug Tracker, https://github.com/Exsplendor/oilvisco/issues
Author-email: splendor <splendor@tuta.io>
Classifier: Development Status :: 5 - Production/Stable
Classifier: License :: OSI Approved :: MIT License
Classifier: Operating System :: OS Independent
Classifier: Programming Language :: Python :: 3
Classifier: Topic :: Scientific/Engineering
Requires-Python: >=3.8
